SwissKnife/__init__.py
SwissKnife/avro/AvroTransformer.py
SwissKnife/avro/AvroWriter.py
SwissKnife/avro/__init__.py
SwissKnife/avro/types.py
SwissKnife/calendar/WeekUtils.py
SwissKnife/calendar/__init__.py
SwissKnife/gcloud/GCloudStorage.py
SwissKnife/gcloud/GCloudStreaming.py
SwissKnife/gcloud/__init__.py
SwissKnife/info/BucketPath.py
SwissKnife/info/ExecutionEnvironment.py
SwissKnife/info/__init__.py
udaswissknife-0.12.0.dist-info/LICENSE
udaswissknife-0.12.0.dist-info/WHEEL
udaswissknife-0.12.0.dist-info/METADATA
udaswissknife-0.12.0.dist-info/RECORD
