Metadata-Version: 2.1
Name: udaswissknife
Version: 0.12.0
Summary: Utils and common libraries for Python
Home-page: https://github.com/urbandataanalytics/SwissKnife
Author: UDARealState Data engineering Team
Requires-Python: >=3.6,<4.0
Classifier: License :: OSI Approved :: MIT License
Classifier: Programming Language :: Python :: 3
Classifier: Programming Language :: Python :: 3.6
Classifier: Programming Language :: Python :: 3.7
Classifier: Programming Language :: Python :: 3.8
Classifier: Programming Language :: Python :: 3.9
Provides-Extra: all
Provides-Extra: avro
Provides-Extra: gcloud
Requires-Dist: backoff (>=1.10,<2.0); extra == "all" or extra == "gcloud"
Requires-Dist: coverage (>=4.5,<5.0)
Requires-Dist: fastavro (>=0.22,<0.23); extra == "all" or extra == "avro"
Requires-Dist: google-cloud-storage (>=1.23,<2.0); extra == "all" or extra == "gcloud"
Requires-Dist: nose (>=1.3,<2.0)
